volumential/__init__.py
volumential/_git_rev.py
volumential/droste.py
volumential/expansion_wrangler_fpnd.py
volumential/expansion_wrangler_interface.py
volumential/function_extension.py
volumential/geometry.py
volumential/list1.py
volumential/list1_gallery.py
volumential/list1_symmetry.py
volumential/meshgen.py
volumential/nearfield_potential_table.py
volumential/singular_integral_2d.py
volumential/symbolic.py
volumential/table_manager.py
volumential/tools.py
volumential/version.py
volumential/volume_fmm.py
volumential/qbfem/__init__.py
volumential/qbfem/mesh.py
volumential-2017.1a0.dist-info/LICENSE.md
volumential-2017.1a0.dist-info/METADATA
volumential-2017.1a0.dist-info/WHEEL
volumential-2017.1a0.dist-info/top_level.txt
volumential-2017.1a0.dist-info/RECORD
