Metadata-Version: 2.1
Name: volumential
Version: 2017.1a0
Summary: Volume potential computation powered by FMM.
Home-page: UNKNOWN
Author: Xiaoyu Wei
Author-email: wxy0516@gmail.com
License: MIT
Platform: UNKNOWN
Classifier: Development Status :: 3 - Alpha
Classifier: Intended Audience :: Developers
Classifier: Intended Audience :: Science/Research
Classifier: License :: OSI Approved :: MIT License
Classifier: Natural Language :: English
Classifier: Programming Language :: Python
Classifier: Topic :: Scientific/Engineering
Classifier: Topic :: Scientific/Engineering :: Information Analysis
Classifier: Topic :: Scientific/Engineering :: Mathematics
Classifier: Topic :: Scientific/Engineering :: Visualization
Classifier: Topic :: Software Development :: Libraries
Classifier: Topic :: Utilities
Requires-Dist: boxtree
Requires-Dist: h5py
Requires-Dist: loo.py
Requires-Dist: meshmode
Requires-Dist: modepy
Requires-Dist: pyevtk
Requires-Dist: pymbolic
Requires-Dist: pytential
Requires-Dist: scipy
Requires-Dist: sumpy
Provides-Extra: doc
Requires-Dist: sphinx ; extra == 'doc'
Requires-Dist: sphinx-rtd-theme ; extra == 'doc'
Provides-Extra: gmsh_support
Requires-Dist: gmsh-interop ; extra == 'gmsh_support'
Provides-Extra: test
Requires-Dist: pytest ; extra == 'test'
Requires-Dist: gmsh-interop ; extra == 'test'
